expandobjects/__init__.py
expandobjects/exceptions.py
expandobjects/expander.py
expandobjects/main.py
pyexpandobjects-0.2.dist-info/DESCRIPTION.rst
pyexpandobjects-0.2.dist-info/METADATA
pyexpandobjects-0.2.dist-info/RECORD
pyexpandobjects-0.2.dist-info/WHEEL
pyexpandobjects-0.2.dist-info/entry_points.txt
pyexpandobjects-0.2.dist-info/metadata.json
pyexpandobjects-0.2.dist-info/top_level.txt
