Metadata-Version: 2.0
Name: pyexpandobjects
Version: 0.2
Summary: EnergyPlus Expand Objects implementation in Python.
Home-page: https://github.com/myoldmopar/py-expandobjects
Author: Edwin Lee
Author-email: edwin.lee@nrel.gov
License: UNKNOWN
Keywords: cli energyplus templates
Platform: UNKNOWN
Classifier: Intended Audience :: Developers
Classifier: Topic :: Utilities
Classifier: License :: Public Domain
Classifier: Natural Language :: English
Classifier: Operating System :: OS Independent
Classifier: Programming Language :: Python
Requires-Dist: pyiddidf (==0.5)
